{
  "id": "cr-scij-1430",
  "type": "statute",
  "title": "Empréstito Municipalidad Alajuela para Planta Eléctrica",
  "title_en": "Empréstito Municipalidad Alajuela para Planta Eléctrica",
  "short_name": "Norma 1430",
  "status": "in_force",
  "issued_date": "1906-07-12",
  "in_force_date": "",
  "url": "https://pgrweb.go.cr/scij/Busqueda/Normativa/Normas/nrm_texto_completo.aspx?nValor1=1&nValor2=1430",
  "description": "Official SCIJ legislation text (nValor2=1430).",
  "provisions": [
    {
      "provision_ref": "art2",
      "section": "2",
      "title": "ARTÍCULO 2. &deg;",
      "content": "Queda así reformado el artículo del mismo número del\ndecreto de 11 de abril de 1905. \n \n Al Poder\nEjecutivo \n \n Dado en el Salón\nde Sesiones del Congreso, Palacio Nacional, San José, a los once\ndías del mes de julio de mil novecientos seis. \n \n San José, a los\ndoce días del mes de julio de mil novecientos seis. \n \n \n \n \n \n Ficha articulo \n \n \n N°39 \n \n \n \n EL\nCONGRESO CONSTITUCIONAL DE LA REPÚBLICA DE COSTA RICA \n \n \n \n A iniciativa del Poder Ejecutivo, \n \n \n \n Decreta:"
    },
    {
      "provision_ref": "art1",
      "section": "1",
      "title": "ARTÍCULO 1. A fin de que la Municipalidad del cantón central de la provincia de Alajuela",
      "content": "arbitre los recursos necesarios para atender a los gastos que demande la\ninstalación propia de una planta eléctrica para el alumbrado de arco e\nincandescente en la ciudad, autorizándosele para que contrate un empréstito\ninterior de treinta mil colones (¢30 000 00) a un tipo de interés que no exceda\ndel diez por ciento anual, y para dar en garantía las rentas de destace y de\nalumbrado. \n \n Ficha articulo \n \nFecha de generación: 22/2/2026 03:22:19"
    }
  ],
  "definitions": []
}
