{
  "id": "cr-scij-2807",
  "type": "statute",
  "title": "Dona Terrenos Temporalidades Iglesia CatĂ³lica en Milla MarĂ­tima Quepos",
  "title_en": "Dona Terrenos Temporalidades Iglesia CatĂ³lica en Milla MarĂ­tima Quepos",
  "short_name": "Norma 2807",
  "status": "in_force",
  "issued_date": "1949-04-06",
  "in_force_date": "",
  "url": "https://pgrweb.go.cr/scij/Busqueda/Normativa/Normas/nrm_texto_completo.aspx?nValor1=1&nValor2=2807",
  "description": "Official SCIJ legislation text (nValor2=2807).",
  "provisions": [
    {
      "provision_ref": "artfull",
      "section": "full",
      "title": "Texto completo",
      "content": "Nï¿½212 \n \n \n \n LA\n JUNTA FUNDADORA DE LA SEGUNDA REPï¿½BLICA \n \n \n \n Considerando: \n \n \n \n I 9 -Que la obligaciï¿½n que el inciso a) del artï¿½culo\n69 del Cï¿½digo de Trabajo, impone a los patronos, resulta en la prï¿½ctica\ndispendiosa y | casa o nula utilidad para los fines tï¿½cnicos de investigaciï¿½n\nestadï¿½stica que el Ministerio de\nTrabajo y Previsiï¿½n Social ha de realizar con base en los datos suministrados. \n \n \n \n 2ï¿½-Que la Comisiï¿½n encargada de estudiar todas\nlas reforma! se han de introducir a\nla legislaciï¿½n de trabajo, harï¿½ un estudio minucioso de ese inciso para\nadecuarlo a las necesidades especï¿½ficas de orden tï¿½cnico que se tuvieron en\nmira al implantarlo. \n \n \n \n 3ï¿½-Que para efectos inmediatos, y hasta tanto no\nentre en vigencia el nuevo texto\nlegal que la Comisiï¿½n recomiende, es de urgente necesidad recabar de los\npatronos una serie de datos que permitan al Ministerio de Trabajo y Previsiï¿½n\nSocial, realizar un estudio detallado de la desocupaciï¿½n, para determinar tï¿½cnicamente\nsus causas y los posibles m combatirla. Por tanto, \n \n \n \n decreta: \n \n \n \n Artï¿½culo 1ï¿½-Suspï¿½ndese la obligaciï¿½n a cargo\nde los patronos estipulada en el inciso a), del artï¿½culo 69 del Cï¿½digo de\nTrabajo. \n \n \n \n Ficha articulo \n Artï¿½culo 2ï¿½-En su lugar, todos los patronos del\npaï¿½s estarï¿½n obligados a suministrar, directamente o por medio de las\nautoridades polï¿½ticas o de trabajo del lugar donde' se encuentre su negocio,\nindustria o empresa, un informe mensual que contenga los datos que se soliciten\nen los formularios que para el efecto proporcionarï¿½ el Instituto Nacional de\ninvestigaciones y de Estudios Sociales del Ministerio de Trabajo, relativos al i\nmiento de trabajadores habido en esos negocios, industrias o empresas. \n \n \n \n Los datos referentes a los meses transcurridos del\npresente aï¿½o. deberï¿½n suministrarse antes del quince de noviembre prï¿½ximo. \n \n \n \n Ficha articulo \n Artï¿½culo 3ï¿½-El presente decreto rige a partir\ndel dï¿½a de su publicaciï¿½n.- \n \n \n \n Dado en el Salï¿½n de Sesiones de la Junta Fundadora\nde la Segunda Repï¿½blica.-San Josï¿½, a los ocho dï¿½as del mes de octubre de\nmi! cientos cuarenta y ocho.- \n \n Ficha articulo \n \nFecha de generaciï¿½n: 22/2/2026 05:03:37"
    }
  ],
  "definitions": []
}
