{
  "id": "cr-scij-4248",
  "type": "statute",
  "title": "Aprueba los actos del Poder Ejecutivo constantes en In Memoria presentada por el Ministro de Hacienda, Guerra y Marina",
  "title_en": "Aprueba los actos del Poder Ejecutivo constantes en In Memoria presentada por el Ministro de Hacienda, Guerra y Marina",
  "short_name": "Norma 4248",
  "status": "in_force",
  "issued_date": "1852-06-08",
  "in_force_date": "",
  "url": "https://pgrweb.go.cr/scij/Busqueda/Normativa/Normas/nrm_texto_completo.aspx?nValor1=1&nValor2=4248",
  "description": "Official SCIJ legislation text (nValor2=4248).",
  "provisions": [
    {
      "provision_ref": "artfull",
      "section": "full",
      "title": "Texto completo",
      "content": "Texto Completo Norma 61 \n \n \n \n \n Aprueba los actos del Poder Ejecutivo constantes en In Memoria presentada por el Ministro de Hacienda, Guerra y Marina \n \n \n \n \n \n \n \n \n \n \n \n \n \n \n \n \n \n Ana Magaly UreĂ±a Vargas \n Normal \n Lina ZĂˇrate Elizondo \n 3 \n 9 \n 2022-11-15T20:33:00Z \n 2022-11-16T21:34:00Z \n 1 \n 210 \n 1158 \n 9 \n 2 \n 1366 \n 16.00 \n \n \n \n \n \n \n \n \n \n false \n \n 21 \n \n false \n false \n false \n \n ES-CR \n X-NONE \n X-NONE \n \n \n \n \n MicrosoftInternetExplorer4 \n \n \n \n \n \n \n \n \n \n \n \n \n \n \n \n \n \n \n \n \n \n \n \n \n \n \n \n \n \n \n \n \n \n \n \n \n \n \n \n \n \n \n \n \n \n \n \n \n \n \n \n \n \n \n \n \n \n \n \n \n \n \n \n \n \n \n \n \n \n \n \n \n \n \n \n \n \n \n \n \n \n \n \n \n \n \n \n \n \n \n \n \n \n \n \n \n \n \n \n \n \n \n \n \n \n \n \n \n \n \n \n \n \n \n \n \n \n \n \n \n \n \n \n \n \n \n \n \n \n \n \n \n \n \n \n \n \n \n \n \n \n \n \n \n \n \n \n \n \n \n \n \n \n \n \n \n \n \n \n \n \n \n \n \n \n \n \n \n \n \n \n \n \n \n \n \n \n \n \n \n \n \n \n \n \n \n \n \n \n \n \n \n \n \n \n \n \n \n \n \n \n \n \n \n \n \n \n \n \n \n \n \n \n \n \n \n \n \n \n \n \n \n \n \n \n \n \n \n \n \n \n \n \n \n \n \n \n \n \n \n \n \n \n \n \n \n \n \n \n \n \n \n \n \n \n \n \n \n \n \n \n \n \n \n \n \n \n \n \n \n \n \n \n \n \n \n \n \n \n \n \n \n \n \n \n \n \n \n \n \n \n \n \n \n \n \n \n \n \n \n \n \n \n \n \n \n \n \n \n \n \n \n \n \n \n \n \n \n \n \n \n \n \n \n \n \n \n \n \n \n \n \n \n \n \n \n \n \n \n \n \n \n \n \n \n \n \n \n \n \n \n \n \n \n \n \n \n \n \n \n \n \n \n \n \n \n \n \n \n \n \n \n \n \n \n \n \n \n \n \n \n \n \n \n \n \n \n \n \n \n \n \n \n \n \n \n \n \n \n \n DECRETO LXI \n \n (Esta norma\nfue derogada por el artĂ­culo 1Â° de la ley NÂ° 10176 del 20 de abril de 2022,\n\"Derogatoria de leyes caducas o histĂłricamente obsoletas para la\ndepuraciĂłn del ordenamiento jurĂ­dico (quinta parte)\") \n \n Aprueba los actos del Poder Ejecutivo constantes en In\nMemoria presentada por el Ministro de Hacienda, Guerra y Marina . \n \n \n \n \"Juan Rafael Mora\nPresidente de la RepĂşblica de Costa Rica, -Por cuanto el ExcelentĂ­simo Congreso\nConstitacional ha decretado lo siguiente. \n \n \n \n El ExcelentĂ­simo\nCongreso Constitucional de la RepĂşblica de Costa Rica, despues de haber\nexaminado la Memeria con que et SeĂ±or Ministro de Hacienda, Guerra v Marina diĂł\ncuenta del estado de los negocios concernientes Ă  los departamentos de su\ncargo, decreta: \n \n \n \n Art. unico. Se aprueban\ntolos los actos del Poder Ejecutivo constantes en la Memoria presentada pOr el\nSeĂ±or Ministro de Hacienda, Guerra y Marina en 18 de mayo proximo pasado. Al\nPoder Ejecutivo. -Dado en el Palacio de los Supremos Poderes en San JosĂ©, Ăˇ los\ncuatro dias del mes de junio de mil ochocientos cincuenta y dos.-Francisco\nMaria Oreamuno, Presidente. - Bruno Carranza, Secretario, JosĂ© Maria Garcia,\nSecretario. -Por tanto: EJECUTESE. Palacio Nacional, San JosĂ© junio ocho de mil\nochocientos cincuenta y dos.-Juan Rafael Mora, El Ministro de Estado en el\nDespacho de Hacienda, Guerra y Marina, Manuel JosĂ© Carazo.\" \n \n Ficha articulo \n \nFecha de generaciĂłn: 22/2/2026 07:08:13"
    }
  ],
  "definitions": []
}
