{
  "id": "cr-scij-9378",
  "type": "statute",
  "title": "Manda trasladar las Autoridades y edificios públicos del Puerto de Puntarenas al de Caldera",
  "title_en": "Manda trasladar las Autoridades y edificios públicos del Puerto de Puntarenas al de Caldera",
  "short_name": "Norma 9378",
  "status": "in_force",
  "issued_date": "1837-03-30",
  "in_force_date": "",
  "url": "https://pgrweb.go.cr/scij/Busqueda/Normativa/Normas/nrm_texto_completo.aspx?nValor1=1&nValor2=9378",
  "description": "Official SCIJ legislation text (nValor2=9378).",
  "provisions": [
    {
      "provision_ref": "artfull",
      "section": "full",
      "title": "Texto completo",
      "content": "Texto Completo Norma 6 \n \n \n \n \n Manda trasladar las Autoridades y edificios públicos del Puerto de Puntarenas al de Caldera \n \n \n \n \n \n \n \n \n \n \n \n \n \n \n \n \n \n Marie Claire Polanco Mora \n Normal \n Lina Zárate Elizondo \n 4 \n 51 \n 2022-07-12T20:04:00Z \n 2022-08-09T17:01:00Z \n 1 \n 345 \n 1899 \n 15 \n 4 \n 2240 \n 16.00 \n \n \n \n \n \n \n \n \n \n Clean \n false \n \n 21 \n \n false \n false \n false \n \n ES-CR \n X-NONE \n X-NONE \n \n \n \n \n MicrosoftInternetExplorer4 \n \n \n \n \n \n \n \n \n \n \n \n \n \n \n \n \n \n \n \n \n \n \n \n \n \n \n \n \n \n \n \n \n \n \n \n \n \n \n \n \n \n \n \n \n \n \n \n \n \n \n \n \n \n \n \n \n \n \n \n \n \n \n \n \n \n \n \n \n \n \n \n \n \n \n \n \n \n \n \n \n \n \n \n \n \n \n \n \n \n \n \n \n \n \n \n \n \n \n \n \n \n \n \n \n \n \n \n \n \n \n \n \n \n \n \n \n \n \n \n \n \n \n \n \n \n \n \n \n \n \n \n \n \n \n \n \n \n \n \n \n \n \n \n \n \n \n \n \n \n \n \n \n \n \n \n \n \n \n \n \n \n \n \n \n \n \n \n \n \n \n \n \n \n \n \n \n \n \n \n \n \n \n \n \n \n \n \n \n \n \n \n \n \n \n \n \n \n \n \n \n \n \n \n \n \n \n \n \n \n \n \n \n \n \n \n \n \n \n \n \n \n \n \n \n \n \n \n \n \n \n \n \n \n \n \n \n \n \n \n \n \n \n \n \n \n \n \n \n \n \n \n \n \n \n \n \n \n \n \n \n \n \n \n \n \n \n \n \n \n \n \n \n \n \n \n \n \n \n \n \n \n \n \n \n \n \n \n \n \n \n \n \n \n \n \n \n \n \n \n \n \n \n \n \n \n \n \n \n \n \n \n \n \n \n \n \n \n \n \n \n \n \n \n \n \n \n \n \n \n \n \n \n \n \n \n \n \n \n \n \n \n \n \n \n \n \n \n \n \n \n \n \n \n \n \n \n \n \n \n \n \n \n \n \n \n \n \n \n \n \n \n \n \n \n \n \n \n \n \n \n \n \n \n \n \n \n \n \n \n \n \n \n \n \n \n \n \n \n \n \n DECRETO\nVI \n \n (Esta norma\nfue derogada por el artículo 1° de la ley N° 10176 del 20 de abril de 2022,\n\"Derogatoria de leyes caducas o históricamente obsoletas para la\ndepuración del ordenamiento jurídico (quinta parte)\") \n \n Manda trasladar las\nAutoridades y edificios públicos del Puerto de Puntarenas al de Caldera (1). \n \n \n \n \" El Jefe\nSupremo Provisorio del Estado libre de Costa Rica. \n \n \n \n Considerando: 1° que\nen virtud de haberse plenamente comprobando la necesidad, utilidad y\nconveniencia de trasladar el Puerto de Puntarenas al antiguo nombrado Caldera,\nla Legislatura del Estado expidió en 21 de marzo de 834 su Decreto autorizando\nal Gobierno, no solo para procurar la misma traslación, sino también para\nponerla en planta, con fondos de la Hacienda Pública, 2° que el Congreso\nNacional oyendo el voto público de Costa Rica lo atendió, dando en consonancia\ncon el su soberana resolución de 23 de Enero de 835 por la se ordena que la\nAdministración marítima del Puerto mayor situado en Puntarenas, se traslade al\ncitado punto de Caldera autorizando al Gobierno Federal para construir en este\nlas oficinas y demás que juzgue necesario al establecimiento del mismo Puerto:\n3° que el cumplimiento del mismo Puerto: 3° que el cumplimiento y ejecución de\ntan interesante medida han estado paralizados por dos años a causa de la falta\nde fondos en la Aduana del Puerto para cubrir los primeros gastos: 4° que cada\ndías se hace más necesario y urgente llevar al cabo la traslación, con motivo\nya de los incendios ocurridos, como de la ruina del edificio de la Aduana: 5° y\nfinalmente que es general el clamor de los interesados en los negocios\nmercantiles porque los Decretos de traslación tengan su cumplido efecto para la\nmayor seguridad de sus intereses en el nuevo, establecimiento, facilidad de\nembarque y desembarque, disminución de caminos y riesgos en él, y proporciones\npara que la población prospere, he venido en decretar y decreto: \n \n \n \n Art 1°.- Se\nconstruirá una Barraca pajiza en el nominado punto de Caldera con la formalidad\ny seguridad posible de tres y media varas de alto, treinta y cinco de largo y\nocho de ancho, con habitaciones superiores, para que el Gobierno Nacional, con\neste auxilio, traslade la administración marítima del Puerto. \n \n Ficha articulo \n \n \n Art 2°.- La\nIntendencia General, de toda preferencia, solicitará a comisionara persona\ninteligente, para que a la mayor posible brevedad haga aquella obra, y llevando\ncuenta y razón exacto de los gastos necesarios para ella, hará se satisfagan en\nla Tesorería General. \n \n Ficha articulo \n \n \n Art 3°.- Para la\ndesignación del mejor punto es que debe situarse aquel edificio y demás preciso\narreglos de la población en el nuevo Puerto, se comisiona al C. Santiago Millet e igualmente para conceder y demarque los primeros\nsolares a los que quieran hacer allí sus casas.. \n \n Ficha articulo \n \n \n Art 4.- El Gobierno\nseguir el temor del Decreto de 22 de marzo de 836, oportunamente nombrara otro\ncomisionado para la concesión de solares gratis, y arreglo de la nueva población,\nen que deben ser las manzanas por todo frente de cien varas y las calles en\nperfecta rectitud y de veinte varas de ancho, intimando a los nuevos pobladores\nel artículo 1° del citado decreto. \n \n Ficha articulo \n \n \n Art 5°.- El\npresente Decreto se imprimirá, y circulará- Dado en la ciudad de San José a los\ntreinta días del mes de marzo de mil ochocientos treinta y siete. \n \n Ficha articulo \n \nFecha de generación: 22/2/2026 18:46:12"
    }
  ],
  "definitions": []
}
