{
  "id": "cr-scij-10746",
  "type": "statute",
  "title": "Prescribe libros para alcaides y jueces civiles",
  "title_en": "Prescribe libros para alcaides y jueces civiles",
  "short_name": "Norma 10746",
  "status": "in_force",
  "issued_date": "1878-02-04",
  "in_force_date": "",
  "url": "https://pgrweb.go.cr/scij/Busqueda/Normativa/Normas/nrm_texto_completo.aspx?nValor1=1&nValor2=10746",
  "description": "Official SCIJ legislation text (nValor2=10746).",
  "provisions": [
    {
      "provision_ref": "artfull",
      "section": "full",
      "title": "Texto completo",
      "content": "Texto Completo Norma 9 \n \n \n \n \n Prescribe libros para alcaides y jueces civiles \n \n \n \n \n \n \n \n \n \n \n \n \n \n \n \n \n \n Ana Magaly Ureña Vargas \n Normal \n Lina Zárate Elizondo \n 6 \n 54 \n 2022-11-22T17:00:00Z \n 2023-02-08T20:03:00Z \n 1 \n 342 \n 1884 \n 15 \n 4 \n 2222 \n 16.00 \n \n \n \n \n \n \n \n \n \n Clean \n false \n \n 21 \n \n false \n false \n false \n \n ES-CR \n X-NONE \n X-NONE \n \n \n \n \n MicrosoftInternetExplorer4 \n \n \n \n \n \n \n \n \n \n \n \n \n \n \n \n \n \n \n \n \n \n \n \n \n \n \n \n \n \n \n \n \n \n \n \n \n \n \n \n \n \n \n \n \n \n \n \n \n \n \n \n \n \n \n \n \n \n \n \n \n \n \n \n \n \n \n \n \n \n \n \n \n \n \n \n \n \n \n \n \n \n \n \n \n \n \n \n \n \n \n \n \n \n \n \n \n \n \n \n \n \n \n \n \n \n \n \n \n \n \n \n \n \n \n \n \n \n \n \n \n \n \n \n \n \n \n \n \n \n \n \n \n \n \n \n \n \n \n \n \n \n \n \n \n \n \n \n \n \n \n \n \n \n \n \n \n \n \n \n \n \n \n \n \n \n \n \n \n \n \n \n \n \n \n \n \n \n \n \n \n \n \n \n \n \n \n \n \n \n \n \n \n \n \n \n \n \n \n \n \n \n \n \n \n \n \n \n \n \n \n \n \n \n \n \n \n \n \n \n \n \n \n \n \n \n \n \n \n \n \n \n \n \n \n \n \n \n \n \n \n \n \n \n \n \n \n \n \n \n \n \n \n \n \n \n \n \n \n \n \n \n \n \n \n \n \n \n \n \n \n \n \n \n \n \n \n \n \n \n \n \n \n \n \n \n \n \n \n \n \n \n \n \n \n \n \n \n \n \n \n \n \n \n \n \n \n \n \n \n \n \n \n \n \n \n \n \n \n \n \n \n \n \n \n \n \n \n \n \n \n \n \n \n \n \n \n \n \n \n \n \n \n \n \n \n \n \n \n \n \n \n \n \n \n \n \n \n \n \n \n \n \n \n \n \n \n \n \n \n \n \n \n \n \n \n \n \n \n \n \n \n \n \n \n \n \n \n \n \n \n \n \n \n \n \n \n \n \n \n \n DECRETO N° IX. \n \n (Esta norma fue derogada por el artículo 1°, inciso 35, de la ley N° 10285 del 20 de setiembre\nde 2022, \"Derogatoria de leyes caducas o históricamente obsoletas para la\ndepuración del ordenamiento jurídico (VII parte)\") \n \n que\nprescribe los libros que deben llevar los Alcaides de cárcel y Jueces civiles,\nmilitares y del crimen. \n \n \n \n TOMAS GUARDIA, General en Jefe del Ejército y Presidente de\nla República de Costa-Rica, considerando: \n \n \n \n 1°-Que la forma en que hasta\nhoy dia se llevan los libros de cárcel no se presta á que los Magistrados de la Suprema Corte de Justicia\npuedan llenar pronta y cumplidamente el objeto de las visitas establecidas por\nla ley. \n \n 2°. - Que de igual\ndeficiencia adolecen las listas de detenidos y presos que presentan los\nAlcaides, y las relaciones de los Jueces sobre el estado de las causas de su\nconocimiento; y \n \n 3°- Que fuera de estos\nvacíos se han notado otros que piden remedio para que el manejo de las oficinas\nde Justicia tenga las condiciones apetecibles de órden \ny seguridad; \n \n \n \n DECRETO: \n \n Art. 1° Los Alcaides de\nlas cárceles llevarán un libro de detenidos, otro de presos y otro de\ncondenados á \narresto ó prisión en ellas. Las planas de dichos\nlibros presentaran á golpe de vista, en cuadros\nadecuadamente combinados, cuando es preciso saber para los debidos efectos de\nla visita. Cada plana del 1° y 2° libros contendrá siete columnas la primera\npara asentar las fechas de entrada del detenido ó \npreso; la segunda para el nombre de éste, ó de cada\nindividuo, si la órden respectiva comprendiere varios\n á la vez; la tercera para la denominacion \ndel delito ò culpa del indiciado; la cuarta para la denominacion \n tambien de la autoridad de quien hubiese procedido la\n órden ; la quinta para el número de dicha órden ; la sexta para la fecha de la salida del detenido o\npreso; y sétima para el número de de la órden de excarcelación. El libro de rematados se arreglará\ndel mismo modo, con la diferencia de llevar una columna más, para sentar en\nseguida de la columna tercera, la pena impuesta, con su tiempo o duración. Los\nAlcaides harán de las órdenes de entradas y salidas que reciban, tres legajos:\nuno referente a las detenciones, otro á las prisiones y otro á las condenaciones. \n \n \n \n \n \n Ficha articulo \n \n \n Art. 2° -Los Jueces obligados à dar cuenta en las visitas de\ncárcel, lo harán presentando un libro que, arreglado en columnas como los\nanteriores, contenga: en una el nombre del indiciado o procesad; en otra, la denominacion del delito o culpa; en otra, la fecha del auto\ncabeza de proceso; en otra, la del de prision ; en\notra, el estado de la causa; y en otra, la fecha desde la cual se halla en ese\nmismo estado. Además al pié \nde la plana en columna transversal estarán las observaciones ó anotaciones áque en su\nrespectivo lugar se llame la atención. \n \n \n \n Ficha articulo \n \n \n Art. 3°-Los Jueces de 1 a Instancia Civil y de\nComercio y los del Crimen, llevarán cada uno un libro de registro para anotar\nla entrada y salida de todos los expedientes de su respectiva oficina, con excepcion de los anteriormente fenecidos ó archivados. En cada plana estarán marcadas seis columnas verlicales y una trasversal, para las explicaciones á que se llame. En las columnas verticales del dominio de\nlos jueces Civiles y de Comercio, la primera será para el número ordinal del\nexpediente; la segunda, para la fecha de su entrada ó \niniciación; la tercera y cuarta para los nombres de los demandantes y\ndemandados principales; la quinta, para exponer suscintamente \nla naturaleza y materia del juicio ó del negocio, si\néste fuere de jurisdicción voluntaria; la sexta para la fecha de salidada del expediente; la sétima para indicar el destino\nque se le ha dado, sea al archivamento , sea de\nentrega a otro funcionario ó al interesado. Las\ncolumnas del dominio de los Jueces del Crimen se llenarán de la propia manera,\ncon la diferencia de que la quinta columna lo que ha de contener es la determinacion del delito ó culpa\npor el cual se procede, con Ia frase precedente de\n\"por acusación, denuncio o de oficio,\" según corresponda. En la cuarta columna,\ndestinada para el nombre del demandado, no figurará el del presunto reo, sino\ndesde que se hubiese dictado contra él, auto de prision.Tampoco \nen las columnas de salida deben anotarse los expedientes que la hubieren\ntenido, por apelación ó súplica, comision ,\n recusacion , impedimento, etc ;\nsino tan sólo los que salieren de una manera definitiva, como por\narchivamiento, incompetencia ó entrega al interesado\ndel del que á su solicitud\nse hubiera instruido en jurisdicción voluntaria. En aquellos casos en que debe\nomitirse la anotacion , ha de justificarse la entrega\ndel expediente con el recibo del caso. \n \n \n \n Ficha articulo \n \n \n Art. 4°-Los Alealdes y Jueces\nMilitares, con excepcion de los especificos ,\nson tambien obligados a llevar los libros determinados\nen el artículo precedente uno para la materia civil y otro para la criminal. \n \n \n \n Ficha articulo \n \n \n Art. 5° Los Jueces del Crimen llevarán ademas \notro libro talonario en que consten las instrucciones que por riguroso turno\ncometan a los Jueces inferiores de su residencia, cuando aquéllos no puedan\nlevantarlas. En el talon deberá quedar el recibo del\ncomisionado; mas cuando la comision fuere el encargo\nsea debidamente evacuado. \n \n \n \n Ficha articulo \n \n \n Art. 6° -Los Jueces de 1 a Instancia, bajo cuya denominacion se comprende en este Decreto los Auditores de\nGuerra y los Alcaldes y Jueces Militares no específicos, deben finalmente\nllevar otro libro, donde copiarán toda órden de\ncitación, comparecencia, etc , á \ncuyo pie constará el recibo de la parte que la pida. \n \n \n \n \n \n Ficha articulo \n \n \n Art. 7° -El arreglo de los modelos necesarios para la formacion de los libros mencionados. Es cargo de los dos\nMagistrados especiales de 3 a Instancia, bajo cuya direccion debe practicarse dicho trabajo. \n \n \n \n \n \n \n \n \n \n Ficha articulo \n \n \n Art. 8 ° En todos los juicios y demas actos del ramo de Justicia, cualquiera que sea su\nnaturaleza, la denominacion de las personas se hará\npor el nombre y apellido paterno y materno de cada uno, siempre que no haya\ninconveniente para ello. La falta de alguno de los dos apellidos se suplirá con\ncualquiera otro más inmediato de su ascendencia materna. \n \n Dado en el Palacio Nacional, en San José, á los cuatro dias del mes de\nfebrero de mil ochocientos setenta y ocho. T. GUARDIA.- El\nSecretario de Estado en el Despacho de Justicia,-José M a \nCastro. \n \n \n \n Ficha articulo \n \nFecha de generación: 22/2/2026 22:53:42"
    }
  ],
  "definitions": []
}
