{
  "id": "cr-scij-14743",
  "type": "statute",
  "title": "Declara haber lugar a formacion de causa contra el Jefe Politico de Heredia Don Manuel Zamora",
  "title_en": "Declara haber lugar a formacion de causa contra el Jefe Politico de Heredia Don Manuel Zamora",
  "short_name": "Norma 14743",
  "status": "in_force",
  "issued_date": "1845-12-05",
  "in_force_date": "",
  "url": "https://pgrweb.go.cr/scij/Busqueda/Normativa/Normas/nrm_texto_completo.aspx?nValor1=1&nValor2=14743",
  "description": "Official SCIJ legislation text (nValor2=14743).",
  "provisions": [
    {
      "provision_ref": "artfull",
      "section": "full",
      "title": "Texto completo",
      "content": "Texto Completo Norma 62 \n \n \n \n \n Declara haber lugar a formacion de causa contra el Jefe Politico de Heredia Don Manuel Zamora \n \n \n \n \n \n \n \n \n \n \n \n \n \n \n \n \n \n Ana Magaly Ureña Vargas \n Normal \n Lina Zárate Elizondo \n 3 \n 16 \n 2022-08-23T15:38:00Z \n 2022-08-23T22:03:00Z \n 1 \n 291 \n 1603 \n 13 \n 3 \n 1891 \n 16.00 \n \n \n \n \n \n \n \n \n \n false \n \n 21 \n \n false \n false \n false \n \n ES-CR \n X-NONE \n X-NONE \n \n \n \n \n MicrosoftInternetExplorer4 \n \n \n \n \n \n \n \n \n \n \n \n \n \n \n \n \n \n \n \n \n \n \n \n \n \n \n \n \n \n \n \n \n \n \n \n \n \n \n \n \n \n \n \n \n \n \n \n \n \n \n \n \n \n \n \n \n \n \n \n \n \n \n \n \n \n \n \n \n \n \n \n \n \n \n \n \n \n \n \n \n \n \n \n \n \n \n \n \n \n \n \n \n \n \n \n \n \n \n \n \n \n \n \n \n \n \n \n \n \n \n \n \n \n \n \n \n \n \n \n \n \n \n \n \n \n \n \n \n \n \n \n \n \n \n \n \n \n \n \n \n \n \n \n \n \n \n \n \n \n \n \n \n \n \n \n \n \n \n \n \n \n \n \n \n \n \n \n \n \n \n \n \n \n \n \n \n \n \n \n \n \n \n \n \n \n \n \n \n \n \n \n \n \n \n \n \n \n \n \n \n \n \n \n \n \n \n \n \n \n \n \n \n \n \n \n \n \n \n \n \n \n \n \n \n \n \n \n \n \n \n \n \n \n \n \n \n \n \n \n \n \n \n \n \n \n \n \n \n \n \n \n \n \n \n \n \n \n \n \n \n \n \n \n \n \n \n \n \n \n \n \n \n \n \n \n \n \n \n \n \n \n \n \n \n \n \n \n \n \n \n \n \n \n \n \n \n \n \n \n \n \n \n \n \n \n \n \n \n \n \n \n \n \n \n \n \n \n \n \n \n \n \n \n \n \n \n \n \n \n \n \n \n \n \n \n \n \n \n \n \n \n \n \n \n \n \n \n \n \n \n \n \n \n \n \n \n \n \n \n \n \n \n \n \n \n \n \n \n \n \n \n \n \n \n \n \n \n \n \n \n \n \n \n \n \n \n \n \n \n \n \n \n \n \n \n \n \n \n \n \n DECRETO LXII. \n \n (Esta norma\nfue derogada por el artículo 1° de la ley N° 10176 del 20 de abril de 2022,\n\"Derogatoria de leyes caducas o históricamente obsoletas para la\ndepuración del ordenamiento jurídico (quinta parte)\") \n \n Declara haber lugar a formacion de causa contra el Jefe\nPolitico de Heredia Don Manuel Zamora. \n \n \"El Senador\nencargado del Supremo Poder Ejecutivo del Estado libre de Costa Rica. Por cuan- \n \n to la Cámara de\nSenadores ha decretado lo siquiente. \n \n \n \n La Cámara de Senadores\ndel Estado libre de Costa Rica : teniendo presente la acusacion hecha por el\nSeñor Antonio Vindas regidor 2° de la Municipalidad de la ciudad de Heredia,\ncontra el Sr. Manuel Zamora Jefe Político accidental de aquel Departamento , y Presidente\nde la Corporacion de dicha ciudad , por injurias graves inferidas por este, al\nante expreso regidor en acto de sesión, y por infraccion de las leyes en cl\nejercicio de sus funciones contraviniendo à lo prescrito en las fracciones 6 a \ny 7 a del art. 296 parte 2 a del Código, al 344 y 371 de la\nmisma parte citada; y à lo que dispone el art. 24 de la ley de 7 de mayo de\n1832; segun todo consta del expediente; y en conformidad de lo que establece el\nI85 de la ley fondamental: con presencia así mismo del dictamen de la comisión\nrespectiva, y de los documentos justifcativos presentados por el acusador : en\nvista tambien de los artículos 583, 584 y 586 parte segunda lib° 3° tit° 29 del\nCódigo general y en uso de las facultades que le concede el § 5° art. 126, el\nfinal del 186 de la Constitución del Estado , ha venido en declarar y declara. \n \n \n \n Art. 1° Ha lugar à\nformacion de causa contra el Jefe Político accidental del departamento de la\nciudad de Heredia y Presidente de la Municipalidad de la misma ciudad, Señor\nManuel Zamora, por injurias graves inferidas á un miembro de aquel cuerpo, y\nexcesos en el ejercicio de sus funciones con infraccion de las leyes. \n \n \n \n Ficha articulo \n \n \n Art. 2. En consecuencia, queda el expresado Zamora suspenso\nde su destino; y sujeto á que lo juzgue el tribunal establecido\npor el art. 122 cap°10 de la ley de 15 de mayo de 1832. - Comuniquese \nal Poder Ejecutivo para que lo haga imprimir circular y publicar.- Dado\nen la ciudad de San José, á los cuatro dias del mes de diciembre de mil ochocientos cuarenta y\ncinco.-Juan Mora, Senador Presidente. -Juan de Dios Zespedes ,\nSecretario. -Por tanto: EJECUTESE. San José, diciembre cinco de mil ochocientos\ncuarenta y cinco. -José Rafael de Gallegos . -Al\nMinistro de relaciones y gobernacion.\" \n \n \n \n Ficha articulo \n \nFecha de generación: 23/2/2026 04:15:51"
    }
  ],
  "definitions": []
}
