{
  "id": "cr-scij-32410",
  "type": "statute",
  "title": "Nombra Miembros Comisión Permanente",
  "title_en": "Nombra Miembros Comisión Permanente",
  "short_name": "Norma 32410",
  "status": "in_force",
  "issued_date": "1895-07-23",
  "in_force_date": "",
  "url": "https://pgrweb.go.cr/scij/Busqueda/Normativa/Normas/nrm_texto_completo.aspx?nValor1=1&nValor2=32410",
  "description": "Official SCIJ legislation text (nValor2=32410).",
  "provisions": [
    {
      "provision_ref": "artunico",
      "section": "único",
      "title": "ARTÍCULO único. Nombrase para miembros propietarios de la Comisión Permanente que debe",
      "content": "funcionar en el receso del Congreso de 1895 y 1896 a los Diputados don Andrés Saénz,\ndon Carlos Saénz, don Victor Orozco, don Ramón Loría\nIglesias y don Félix Pacheco, y para suplentes a dos Diputados don Juan Rafael\nLizano, don Policarpo Trejos y don Felipe Gallegos. \n \n \n \n Al\nPoder Ejecutivo \n \n \n \n Dado\nen el Salón de Sesiones del Congreso, Palacio Nacional, San José a veintidós de\njulio de mil ochocientos noventa y cinco. \n \n \n \n Palacio\nNacional, San José veintitrés de julio de mil ochocientos noventa y cinco. \n \n \n \n Ficha articulo \n \nFecha de generación: 24/2/2026 03:11:14"
    }
  ],
  "definitions": []
}
