{
  "id": "cr-scij-36208",
  "type": "statute",
  "title": "Reforma artículos 13 y 114 de la Ley Orgánica del Sistema BancarioNacional Nº 1644.",
  "title_en": "Reforma artículos 13 y 114 de la Ley Orgánica del Sistema BancarioNacional Nº 1644.",
  "short_name": "Norma 36208",
  "status": "in_force",
  "issued_date": "1963-04-09",
  "in_force_date": "",
  "url": "https://pgrweb.go.cr/scij/Busqueda/Normativa/Normas/nrm_texto_completo.aspx?nValor1=1&nValor2=36208",
  "description": "Official SCIJ legislation text (nValor2=36208).",
  "provisions": [
    {
      "provision_ref": "art1",
      "section": "1",
      "title": "ARTÍCULO 1. - Refórmanse los artículos 13 y 114 de la Ley Orgánica del",
      "content": "Sistema Bancario Nacional, Nº 1644 de 26 de setiembre de 1953, para que en\n \n lo futuro se lean así:"
    },
    {
      "provision_ref": "art113",
      "section": "113",
      "title": "ARTÍCULO 113. -Los Bancos Comerciales podrán aceptar y avalar",
      "content": "letras de cambio y otros documentos de crédito girados contra ellos mismos\n \n o contra personas, y expedir cartas de crédito, siempre que unos y otros\n \n tengan un plazo de vencimiento que no exceda de un año.\n \n También podrán los Bancos Comerciales garantizar obligaciones por\n \n cuenta de terceros, cuyos plazos u otras condiciones serán fijados de\n \n manera general por el Banco Central.\n \n Cuando las operaciones a que se refiere este artículo no se realicen\n \n mediante la entrega efectiva de las sumas aceptadas o garantizadas por el\n \n Banco, quedarán sujetas a los preceptos legales y reglamentarios\n \n aplicables a la concesión de créditos."
    },
    {
      "provision_ref": "art114",
      "section": "114",
      "title": "ARTÍCULO 114. -Las obligaciones que contraigan y los pagos que",
      "content": "realicen los Bancos Comerciales por cuenta y bajo responsabilidad de\n \n Bancos del exterior, no estarán necesariamente sujetos a los requisitos a\n \n que se refiere el artículo 113 anterior, pero si a los que dicte el Banco\n \n Central para esa clase de operaciones.\n \n Ficha articulo"
    },
    {
      "provision_ref": "art2",
      "section": "2",
      "title": "ARTÍCULO 2. - Esta ley rige a partir de su publicación.",
      "content": "Ficha articulo \n \nFecha de generación: 25/2/2026 01:19:33"
    }
  ],
  "definitions": []
}
