{
  "id": "cr-scij-37308",
  "type": "statute",
  "title": "Condiciona Libre Exportación de Fósforos",
  "title_en": "Condiciona Libre Exportación de Fósforos",
  "short_name": "Norma 37308",
  "status": "in_force",
  "issued_date": "1947-12-26",
  "in_force_date": "",
  "url": "https://pgrweb.go.cr/scij/Busqueda/Normativa/Normas/nrm_texto_completo.aspx?nValor1=1&nValor2=37308",
  "description": "Official SCIJ legislation text (nValor2=37308).",
  "provisions": [
    {
      "provision_ref": "artfull",
      "section": "full",
      "title": "Texto completo",
      "content": "Texto Completo Norma 1106 \n \n \n \n \n Condiciona Libre Exportación de Fósforos \n \n \n \n \n \n \n \n \n \n \n Texto no disponible\n Ficha articulo \n \nFecha de generación: 25/2/2026 05:47:35"
    }
  ],
  "definitions": []
}
