{
  "id": "cr-scij-37775",
  "type": "statute",
  "title": "Autoriza Gastos por Terremoto de Nicaragua",
  "title_en": "Autoriza Gastos por Terremoto de Nicaragua",
  "short_name": "Norma 37775",
  "status": "in_force",
  "issued_date": "1931-04-15",
  "in_force_date": "",
  "url": "https://pgrweb.go.cr/scij/Busqueda/Normativa/Normas/nrm_texto_completo.aspx?nValor1=1&nValor2=37775",
  "description": "Official SCIJ legislation text (nValor2=37775).",
  "provisions": [
    {
      "provision_ref": "artfull",
      "section": "full",
      "title": "Texto completo",
      "content": "Texto Completo Norma 47 \n \n \n \n \n Autoriza Gastos por Terremoto de Nicaragua \n \n \n \n \n \n \n \n \n \n \n Texto Completo acta: 31EC8 \n 1 \n \n \n N§ 47\n \n EL CONGRESO CONSTITUCIONAL DE LA REPUBLICA DE\n \n COSTA RICA\n \n DECRETA:\n \n ART&Ouml;CULO 1§.-Los licores, aguardientes, cordiales o aperitivos\n \n alcoh¢licos, vinos sint,ticos, vinos adicionales con sustancias\n \n vegetales\n \n o esencias arom ticas, vinos espumosos, vinos medicinales, y todas\n \n las dem s bebidas alcoh¢licas o espirituosas similares, s¢lo podr n\n \n ser importados en envases de una capacidad no mayor de un litro.\n \n Ficha articulo \n ART&Ouml;CULO 2§.-Los vinos naturales no comprendidos en el\n \n art¡culo\n \n anterior podr n ser importados tambi,n en barriles o damajuanas,\n \n pero con sujeci¢n a las disposiciones de este decreto.\n \n Ficha articulo \n ART&Ouml;CULO 3§.-Los licores y vinos indicados en los art¡culos\n \n anteriores\n \n deber n llevar un timbre fiscal de identificaci¢n, cuya figura y\n \n dise¤o determinar la Secretar¡a de Hacienda y Comercio. Dicho\n \n timbre ser adherido en forma tal a cada una de las botellas o\n \n vasijas\n \n en que se expenden usualmente al p£blico esos licores, que sea\n \n necesariamente\n \n roto al descorchar o abrir la botella o vasija.\n \n Ficha articulo \n ART&Ouml;CULO 4§.-Para los efectos del art¡culo anterior la\n \n Secretar¡a\n \n de Hacienda y Comercio emitir la cantidad necesaria de especies\n \n que ser n de dos clases, valdr n diez y cinco c,ntimos cada una\n \n y se aplicar n respectivamente a los licores indicados en los\n \n art¡culos\n \n 1§ y 2§ de esta ley. Estos sellos ser n depositados en la\n \n Administraci¢n\n \n Principal de Rentas que no los entregar a los interesados si no\n \n es con autorizaci¢n expresa que en cada caso otorgar al\n \n Administrador\n \n de la Aduana en donde se vaya a verificar el desalmacenaje de la\n \n mercader¡a importada.\n \n Ficha articulo \n ART&Ouml;CULO 5§.-Los Administradores de Aduana antes de permitir\n \n el desalmacenaje de las mercader¡as indicadas en los art¡culos 1§\n \n y 2§\n \n de esta ley, dar n una autorizaci¢n escrita a los interesados para\n \n que\n \n puedan adquirir el n£mero de timbres de identificaci¢n de la clase\n \n que corresponda en la cantidad necesaria para que se cumplan las\n \n disposiciones de esta ley. Con ese objeto, cuando se importen\n \n vinos\n \n naturales en barriles o damajuanas, el interesado declarar al\n \n Administrador\n \n de la Aduana por escrito que se tendr como declaraci¢n\n \n jurada, el contenido exacto de cada uno de los recipientes, as¡\n \n como\n \n el n£mero de envases en que piensa distribuirlos, cuya capacidad\n \n indicar \n \n tambi,n.\n \n Y si se tratare de importaci¢n de vinos u otras bebidas\n \n alcoh¢licas\n \n en envases de capacidad no mayor de un litro, el Administrador\n \n de la Aduana exigir que antes de que se proceda al desalmacenaje\n \n se\n \n adhiera a cada botella el sello adquirido conforme al p rrafo\n \n primero\n \n de este art¡culo.\n \n Ficha articulo \n ART&Ouml;CULO 6§.-Los licores y vinos extranjeros importados sin\n \n ajustarse\n \n a los tr mites de este decreto ser n tenidos como licores de\n \n il¡cita\n \n procedencia; y la persona en cuyo poder se hallare cualquier\n \n botella\n \n o envase conteniendo licores enumerados en los art¡culos 1§ y 2§,\n \n sin el sello correspondiente, sufrir por ese solo hecho, el m ximo\n \n de la pena se¤alada al reo de dep¢sitos de licores de il¡cita\n \n procedencia.\n \n En el mismo concepto se tendr n los vinos cuyo an lisis demuestre\n \n que son fabricados con alcohol industrial o de ca¤a y no con\n \n alcohol\n \n v¡nico.\n \n Ficha articulo \n ART&Ouml;CULO 7§.-El comerciante que cometiere falsedad al declarar\n \n el n£mero, capacidad o contenido de los envases importados; el que\n \n solicitare mayor n£mero de timbres de identificaci¢n; el que\n \n intentare\n \n usar los sellos m s de una vez, o tratare en cualquier otra forma\n \n de\n \n burlar la ley, ser castigado con el doble de la pena que\n \n corresponda\n \n a la simple falta de sello.\n \n Ficha articulo \n ART&Ouml;CULO 8§.-En caso de duda acerca de la procedencia de un\n \n licor\n \n que se expenda como extranjero, el interesado deber mostrar la\n \n factura y documentos originales, quedando a juicio de la Secretar¡a\n \n de Hacienda y Comercio, verificar la veracidad de los mismos.\n \n Ficha articulo \n ART&Ouml;CULO 9§.-Queda absolutamente prohibido el desalmacenaje\n \n de las esencias o aceites esenciales que se usen en la fabricaci¢n\n \n de licores\n \n y vinos extranjeros.\n \n Ficha articulo \n ART&Ouml;CULO 10.-Esta ley entrar en vigencia desde el d¡a que la\n \n Secretar¡a de Hacienda y Comercio manifieste tener en existencia la\n \n cantidad suficiente de timbres de identificaci¢n por medio de aviso\n \n que\n \n publicar en el Diario Oficial. A ese efecto, los comerciantes que\n \n tuvieren\n \n en existencia cualquier cantidad de licores que requieran sellos\n \n de identificaci¢n conforme a esta ley proceder n a declararlos ante\n \n la\n \n Administraci¢n General de Licores dentro de los treinta d¡as\n \n posteriores\n \n a la publicaci¢n del aviso referido. Revisada su declaraci¢n por\n \n los\n \n Resguardos Fiscales, adherir n a cada envase el timbre que\n \n contempla\n \n este decreto.\n \n \u001a\n \n Ficha articulo \n \nFecha de generación: 25/2/2026 07:41:26"
    }
  ],
  "definitions": []
}
